openstack_image_manager/__init__.py
openstack_image_manager/main.py
openstack_image_manager/etc/__init__.py
openstack_image_manager/etc/schema.yaml
openstack_image_manager/etc/images/almalinux.yml
openstack_image_manager/etc/images/centos.yml
openstack_image_manager/etc/images/cirros.yml
openstack_image_manager/etc/images/debian.yml
openstack_image_manager/etc/images/fedora.yml
openstack_image_manager/etc/images/flatcar.yml
openstack_image_manager/etc/images/gardenlinux.yml
openstack_image_manager/etc/images/opensuse.yml
openstack_image_manager/etc/images/opnsense.yml
openstack_image_manager/etc/images/rockylinux.yml
openstack_image_manager/etc/images/talos.yml
openstack_image_manager/etc/images/ubuntu.yml
openstack_image_manager-0.20251109.0.dist-info/licenses/LICENSE
openstack_image_manager-0.20251109.0.dist-info/METADATA
openstack_image_manager-0.20251109.0.dist-info/WHEEL
openstack_image_manager-0.20251109.0.dist-info/entry_points.txt
openstack_image_manager-0.20251109.0.dist-info/top_level.txt
openstack_image_manager-0.20251109.0.dist-info/RECORD
