Metadata-Version: 2.4
Name: openstack-image-manager
Version: 0.20251109.0
Summary: OpenStack image manager
Author-email: OSISM community <info@osism.tech>
License:                                  Apache License
Project-URL: Homepage, https://github.com/osism/openstack-image-manager
Project-URL: Bug Tracker, https://github.com/osism/openstack-image-manager/issues
Classifier: Development Status :: 5 - Production/Stable
Classifier: Environment :: Console
Classifier: Intended Audience :: Information Technology
Classifier: License :: OSI Approved :: Apache Software License
Classifier: Operating System :: OS Independent
Classifier: Programming Language :: Python
Classifier: Programming Language :: Python :: 3 :: Only
Classifier: Programming Language :: Python :: 3
Classifier: Programming Language :: Python :: 3.8
Classifier: Programming Language :: Python :: 3.9
Classifier: Programming Language :: Python :: 3.10
Classifier: Programming Language :: Python :: 3.11
Requires-Python: >=3.8
License-File: LICENSE
Requires-Dist: loguru==0.7.3
Requires-Dist: minio==7.2.18
Requires-Dist: munch==4.0.0
Requires-Dist: natsort==8.4.0
Requires-Dist: openstacksdk==4.7.1
Requires-Dist: paramiko==4.0.0
Requires-Dist: patool==4.0.2
Requires-Dist: requests==2.32.5
Requires-Dist: ruamel.yaml==0.18.16
Requires-Dist: setuptools==80.9.0
Requires-Dist: tabulate==0.9.0
Requires-Dist: typer[all]==0.20.0
Requires-Dist: yamale==6.0.0
Dynamic: license-file
